ni_measurement_plugin_sdk/__init__.py
ni_measurement_plugin_sdk-3.1.0.dist-info/METADATA
ni_measurement_plugin_sdk-3.1.0.dist-info/WHEEL
ni_measurement_plugin_sdk-3.1.0.dist-info/RECORD
