Metadata-Version: 2.3
Name: ni_measurement_plugin_sdk
Version: 3.1.0
Summary: Measurement Plug-In SDK for Python
License: MIT
Author: NI
Author-email: opensource@ni.com
Requires-Python: >=3.10,<4.0
Classifier: Development Status :: 5 - Production/Stable
Classifier: Intended Audience :: Developers
Classifier: Intended Audience :: Manufacturing
Classifier: Intended Audience :: Science/Research
Classifier: License :: OSI Approved :: MIT License
Classifier: Operating System :: Microsoft :: Windows
Classifier: Programming Language :: Python :: 3
Classifier: Programming Language :: Python :: 3.10
Classifier: Programming Language :: Python :: 3.11
Classifier: Programming Language :: Python :: 3.12
Classifier: Programming Language :: Python :: 3.13
Classifier: Programming Language :: Python :: Implementation :: CPython
Classifier: Topic :: Scientific/Engineering
Classifier: Topic :: System :: Hardware
Requires-Dist: ni-measurement-plugin-sdk-generator
Requires-Dist: ni-measurement-plugin-sdk-service
Project-URL: Repository, https://github.com/ni/measurement-plugin-python/
